{
  "type": "MutexState",
  "algorithm": "RA",
  "mode": "interactive",
  "processes": [
    {
      "id": "P2",
      "requesting": false,
      "inCS": true,
      "crashed": false,
      "clock": 4,
      "reqTs": 1,
      "awaiting": [],
      "deferred": [
        "P10"
      ]
    },
    {
      "id": "P10",
      "requesting": true,
      "inCS": false,
      "crashed": false,
      "clock": 3,
      "reqTs": 1,
      "awaiting": [
        "P2"
      ],
      "deferred": []
    }
  ],
  "ring": [
    "P2",
    "P10"
  ],
  "network": {
    "nextMsgId": 4,
    "dropNextSend": false,
    "queue": []
  },
  "derived": {
    "inCS": "P2",
    "metrics": {
      "csEntries": 1,
      "csReleases": 0,
      "messagesSent": 3,
      "messagesDelivered": 3,
      "messagesDropped": 0
    }
  }
}